docs/.buildinfo
docs/.nojekyll
docs/api_documentation.html
docs/contributing.html
docs/genindex.html
docs/index.html
docs/installation.html
docs/objects.inv
docs/py-modindex.html
docs/search.html
docs/searchindex.js
docs/usage.html
ghevaluator/__init__.py
ghevaluator/__main__.py
src/docs/conf.py
tests/test_ghevaluator.py
ghevaluator-2.1.1.dist-info/LICENSE
ghevaluator-2.1.1.dist-info/METADATA
ghevaluator-2.1.1.dist-info/WHEEL
ghevaluator-2.1.1.dist-info/entry_points.txt
ghevaluator-2.1.1.dist-info/top_level.txt
ghevaluator-2.1.1.dist-info/RECORD
