Metadata-Version: 2.1
Name: ghevaluator
Version: 2.1.1
Summary: A command-line Python tool to compare Galaxy histories to a template workflow and generate a JSON report file.
Author: Teresa Müller
Author-email: Siyu Chen <chensy96@gmail.com>, Bérénice Batut <berenice.batut@gmail.com>
License: MIT License
Project-URL: repository, https://github.com/SteetScienceCommunity/ghevaluator
Project-URL: documentation, https://streetscience.community/ghevaluator/
Classifier: Programming Language :: Python :: 3
Classifier: License :: OSI Approved :: MIT License
Classifier: Operating System :: OS Independent
Classifier: Topic :: Scientific/Engineering
Requires-Python: >=3.7
License-File: LICENSE
Requires-Dist: bioblend
Requires-Dist: requests
Requires-Dist: Jinja2
